fpapicli/__init__.py
fpapicli/fpapicli.py
fpapicli-1.0.1.dist-info/LICENSE.txt
fpapicli-1.0.1.dist-info/METADATA
fpapicli-1.0.1.dist-info/WHEEL
fpapicli-1.0.1.dist-info/entry_points.txt
fpapicli-1.0.1.dist-info/top_level.txt
fpapicli-1.0.1.dist-info/RECORD
