Metadata-Version: 2.1
Name: fpapicli
Version: 1.0.1
Summary: CLI for Football Player API
Home-page: https://github.com/pranavvp10/fpapicli
Author: Pranav V P
Author-email: pranavvp07@gmail.com
License: UNKNOWN
Keywords: python,cli,api
Platform: UNKNOWN
Classifier: Development Status :: 3 - Alpha
Classifier: Intended Audience :: Education
Classifier: Programming Language :: Python :: 2
Classifier: Programming Language :: Python :: 3
Classifier: Operating System :: MacOS :: MacOS X
Classifier: Operating System :: Microsoft :: Windows
Classifier: License :: OSI Approved :: MIT License
Requires-Dist: Click
Requires-Dist: Requests
